[
  {
    "id": "265c2db15589",
    "provider": "shopify",
    "sync_type": "products",
    "connection_id": "",
    "status": "success",
    "items_synced": 0,
    "items_created": 0,
    "items_updated": 0,
    "items_failed": 0,
    "last_cursor": "",
    "started_at": 1780386240.5878532,
    "finished_at": 1780386240.5880072,
    "error": "",
    "config": {}
  },
  {
    "id": "4173b5fc0421",
    "provider": "shopify",
    "sync_type": "orders",
    "connection_id": "",
    "status": "success",
    "items_synced": 0,
    "items_created": 0,
    "items_updated": 0,
    "items_failed": 0,
    "last_cursor": "",
    "started_at": 1780386240.5960987,
    "finished_at": 1780386240.5961685,
    "error": "",
    "config": {}
  },
  {
    "id": "dd3b77ce4023",
    "provider": "shopify",
    "sync_type": "inventory",
    "connection_id": "",
    "status": "success",
    "items_synced": 0,
    "items_created": 0,
    "items_updated": 0,
    "items_failed": 0,
    "last_cursor": "",
    "started_at": 1780386240.603819,
    "finished_at": 1780386240.603915,
    "error": "",
    "config": {}
  },
  {
    "id": "77489f6ba544",
    "provider": "shopify",
    "sync_type": "products",
    "connection_id": "",
    "status": "success",
    "items_synced": 0,
    "items_created": 0,
    "items_updated": 0,
    "items_failed": 0,
    "last_cursor": "",
    "started_at": 1780397052.2544858,
    "finished_at": 1780397052.255608,
    "error": "",
    "config": {}
  },
  {
    "id": "5a3feb0d2e35",
    "provider": "shopify",
    "sync_type": "orders",
    "connection_id": "",
    "status": "success",
    "items_synced": 0,
    "items_created": 0,
    "items_updated": 0,
    "items_failed": 0,
    "last_cursor": "",
    "started_at": 1780397052.9019675,
    "finished_at": 1780397052.9020555,
    "error": "",
    "config": {}
  },
  {
    "id": "f6ff9afac824",
    "provider": "shopify",
    "sync_type": "inventory",
    "connection_id": "",
    "status": "success",
    "items_synced": 0,
    "items_created": 0,
    "items_updated": 0,
    "items_failed": 0,
    "last_cursor": "",
    "started_at": 1780397052.9090352,
    "finished_at": 1780397052.9091868,
    "error": "",
    "config": {}
  },
  {
    "id": "af25962b1cfe",
    "provider": "shopify",
    "sync_type": "products",
    "connection_id": "",
    "status": "success",
    "items_synced": 0,
    "items_created": 0,
    "items_updated": 0,
    "items_failed": 0,
    "last_cursor": "",
    "started_at": 1780410897.9224691,
    "finished_at": 1780410897.9226298,
    "error": "",
    "config": {}
  },
  {
    "id": "e291d7c63087",
    "provider": "shopify",
    "sync_type": "orders",
    "connection_id": "",
    "status": "success",
    "items_synced": 0,
    "items_created": 0,
    "items_updated": 0,
    "items_failed": 0,
    "last_cursor": "",
    "started_at": 1780410897.9316533,
    "finished_at": 1780410897.9317508,
    "error": "",
    "config": {}
  },
  {
    "id": "91704b1b7ef8",
    "provider": "shopify",
    "sync_type": "inventory",
    "connection_id": "",
    "status": "success",
    "items_synced": 0,
    "items_created": 0,
    "items_updated": 0,
    "items_failed": 0,
    "last_cursor": "",
    "started_at": 1780410897.9388974,
    "finished_at": 1780410897.939013,
    "error": "",
    "config": {}
  },
  {
    "id": "b047ea8af45a",
    "provider": "shopify",
    "sync_type": "products",
    "connection_id": "",
    "status": "success",
    "items_synced": 0,
    "items_created": 0,
    "items_updated": 0,
    "items_failed": 0,
    "last_cursor": "",
    "started_at": 1780452827.418867,
    "finished_at": 1780452827.4190366,
    "error": "",
    "config": {}
  },
  {
    "id": "7b5cccd53f16",
    "provider": "shopify",
    "sync_type": "orders",
    "connection_id": "",
    "status": "success",
    "items_synced": 0,
    "items_created": 0,
    "items_updated": 0,
    "items_failed": 0,
    "last_cursor": "",
    "started_at": 1780452827.424903,
    "finished_at": 1780452827.4249704,
    "error": "",
    "config": {}
  },
  {
    "id": "f3186ae5a742",
    "provider": "shopify",
    "sync_type": "inventory",
    "connection_id": "",
    "status": "success",
    "items_synced": 0,
    "items_created": 0,
    "items_updated": 0,
    "items_failed": 0,
    "last_cursor": "",
    "started_at": 1780452827.4296165,
    "finished_at": 1780452827.4296803,
    "error": "",
    "config": {}
  },
  {
    "id": "7c9381e87a51",
    "provider": "17track",
    "sync_type": "tracking",
    "connection_id": "",
    "status": "success",
    "items_synced": 0,
    "items_created": 0,
    "items_updated": 0,
    "items_failed": 0,
    "last_cursor": "",
    "started_at": 1780453427.4255035,
    "finished_at": 1780453427.4256327,
    "error": "",
    "config": {}
  },
  {
    "id": "e4813b19d868",
    "provider": "shopify",
    "sync_type": "products",
    "connection_id": "",
    "status": "success",
    "items_synced": 0,
    "items_created": 0,
    "items_updated": 0,
    "items_failed": 0,
    "last_cursor": "",
    "started_at": 1780457402.7914362,
    "finished_at": 1780457402.7916327,
    "error": "",
    "config": {}
  },
  {
    "id": "7823e1ffc9b8",
    "provider": "shopify",
    "sync_type": "orders",
    "connection_id": "",
    "status": "success",
    "items_synced": 0,
    "items_created": 0,
    "items_updated": 0,
    "items_failed": 0,
    "last_cursor": "",
    "started_at": 1780457402.798095,
    "finished_at": 1780457402.798197,
    "error": "",
    "config": {}
  },
  {
    "id": "2897c47bb41a",
    "provider": "shopify",
    "sync_type": "inventory",
    "connection_id": "",
    "status": "success",
    "items_synced": 0,
    "items_created": 0,
    "items_updated": 0,
    "items_failed": 0,
    "last_cursor": "",
    "started_at": 1780457402.8038044,
    "finished_at": 1780457402.803905,
    "error": "",
    "config": {}
  },
  {
    "id": "9af8c65a39a3",
    "provider": "17track",
    "sync_type": "tracking",
    "connection_id": "",
    "status": "success",
    "items_synced": 0,
    "items_created": 0,
    "items_updated": 0,
    "items_failed": 0,
    "last_cursor": "",
    "started_at": 1780458002.7901945,
    "finished_at": 1780458002.790358,
    "error": "",
    "config": {}
  },
  {
    "id": "ade869110f26",
    "provider": "shopify",
    "sync_type": "products",
    "connection_id": "",
    "status": "success",
    "items_synced": 0,
    "items_created": 0,
    "items_updated": 0,
    "items_failed": 0,
    "last_cursor": "",
    "started_at": 1780458602.8126738,
    "finished_at": 1780458602.8128488,
    "error": "",
    "config": {}
  },
  {
    "id": "8878eda2c6d1",
    "provider": "shopify",
    "sync_type": "orders",
    "connection_id": "",
    "status": "success",
    "items_synced": 0,
    "items_created": 0,
    "items_updated": 0,
    "items_failed": 0,
    "last_cursor": "",
    "started_at": 1780458602.8234746,
    "finished_at": 1780458602.8236253,
    "error": "",
    "config": {}
  },
  {
    "id": "c6cd34319d9f",
    "provider": "shopify",
    "sync_type": "inventory",
    "connection_id": "",
    "status": "success",
    "items_synced": 0,
    "items_created": 0,
    "items_updated": 0,
    "items_failed": 0,
    "last_cursor": "",
    "started_at": 1780458602.8326619,
    "finished_at": 1780458602.8327885,
    "error": "",
    "config": {}
  },
  {
    "id": "c253950e34e2",
    "provider": "17track",
    "sync_type": "tracking",
    "connection_id": "",
    "status": "success",
    "items_synced": 0,
    "items_created": 0,
    "items_updated": 0,
    "items_failed": 0,
    "last_cursor": "",
    "started_at": 1780460554.0288997,
    "finished_at": 1780460554.0312016,
    "error": "",
    "config": {}
  },
  {
    "id": "b2d8cbb22820",
    "provider": "17track",
    "sync_type": "tracking",
    "connection_id": "",
    "status": "success",
    "items_synced": 0,
    "items_created": 0,
    "items_updated": 0,
    "items_failed": 0,
    "last_cursor": "",
    "started_at": 1780460691.8817492,
    "finished_at": 1780460691.8858118,
    "error": "",
    "config": {}
  },
  {
    "id": "15a4938a916d",
    "provider": "17track",
    "sync_type": "tracking",
    "connection_id": "",
    "status": "success",
    "items_synced": 0,
    "items_created": 0,
    "items_updated": 0,
    "items_failed": 0,
    "last_cursor": "",
    "started_at": 1780460852.1095676,
    "finished_at": 1780460852.1155205,
    "error": "",
    "config": {}
  },
  {
    "id": "ae508f0735cd",
    "provider": "17track",
    "sync_type": "tracking",
    "connection_id": "",
    "status": "success",
    "items_synced": 0,
    "items_created": 0,
    "items_updated": 0,
    "items_failed": 0,
    "last_cursor": "",
    "started_at": 1780461111.9498456,
    "finished_at": 1780461111.9543164,
    "error": "",
    "config": {}
  }
]